<?xml version="1.0" encoding="utf-8" ?><dwsync><file name="style.css" server="hermes.waketech.edu/public_html/" local="3761157128" remote="3761652615" Dst="-1" /><file name="about_me.html" server="hermes.waketech.edu/public_html/" local="3761156942" remote="3761652615" Dst="-1" /><file name="contact.html" server="hermes.waketech.edu/public_html/" local="3761155641" remote="3761653061" Dst="-1" /><file name="index.html" server="hermes.waketech.edu/public_html/" local="3761155927" remote="3761653061" Dst="-1" /><file name="projects.html" server="hermes.waketech.edu/public_html/" local="3761156448" remote="3761653061" Dst="-1" /><file name="style.css" server="Macintosh HD/Users/connormayer/Desktop/su_mayer" local="3761157128" remote="3761157128" Dst="-1" /><file name="contact.html" server="Macintosh HD/Users/connormayer/Desktop/su_mayer" local="3761155641" remote="3761155641" Dst="-1" /><file name="index.html" server="Macintosh HD/Users/connormayer/Desktop/su_mayer" local="3761155927" remote="3761155927" Dst="-1" /></dwsync>